AUTHORS.rst
CONTRIBUTING.rst
LICENSE
MANIFEST.in
README.rst
setup.cfg
setup.py
docs/Makefile
docs/authors.rst
docs/conf.py
docs/contributing.rst
docs/history.rst
docs/index.rst
docs/installation.rst
docs/make.bat
docs/readme.rst
docs/usage.rst
nobeldb/__init__.py
nobeldb/cli.py
nobeldb.egg-info/PKG-INFO
nobeldb.egg-info/SOURCES.txt
nobeldb.egg-info/dependency_links.txt
nobeldb.egg-info/entry_points.txt
nobeldb.egg-info/not-zip-safe
nobeldb.egg-info/requires.txt
nobeldb.egg-info/top_level.txt
nobeldb/data/nobel.csv
tests/__init__.py