Metadata-Version: 1.1
Name: nobeldb
Version: 0.2.0
Summary: Nobel Prize Winner DB Shenanigans
Home-page: https://github.com/ionrock/nobeldb
Author: Eric Larson
Author-email: eric@ionrock.org
License: BSD
Keywords: nobeldb
Platform: UNKNOWN
Classifier: Development Status :: 2 - Pre-Alpha
Classifier: Intended Audience :: Developers
Classifier: License :: OSI Approved :: BSD License
Classifier: Natural Language :: English
Classifier: Programming Language :: Python :: 2
Classifier: Programming Language :: Python :: 2.6
Classifier: Programming Language :: Python :: 2.7
Classifier: Programming Language :: Python :: 3
Classifier: Programming Language :: Python :: 3.3
Classifier: Programming Language :: Python :: 3.4
